nose_deadline.py
setup.cfg
setup.py
nose_deadline.egg-info/PKG-INFO
nose_deadline.egg-info/SOURCES.txt
nose_deadline.egg-info/dependency_links.txt
nose_deadline.egg-info/entry_points.txt
nose_deadline.egg-info/pbr.json
nose_deadline.egg-info/requires.txt
nose_deadline.egg-info/top_level.txt