Metadata-Version: 1.0
Name: nose-deadline
Version: 0.1.0
Summary: Enforced timelimits for nosetests
Home-page: UNKNOWN
Author: Manuel Schoelling
Author-email: manuel.schoelling@gmx.de
License: UNKNOWN
Platform: UNKNOWN
